{"jobs":[{"island":"week03","contract":{"start":{"x":1,"h":"SOUTH","y":1},"budget":20000,"crew":15,"objs":[[{"res":"FLOWER","amount":40},{"res":"WOOD","amount":5000},{"res":"QUARTZ","amount":200},{"res":"GLASS","amount":50}]]}},{"island":"week04","contract":{"start":{"x":1,"h":"EAST","y":1},"budget":10000,"crew":25,"objs":[[{"res":"FUR","amount":1000},{"res":"WOOD","amount":4000},{"res":"GLASS","amount":100}]]}},{"island":"week06","contract":{"start":{"x":1,"h":"NORTH","y":159},"budget":20000,"crew":25,"objs":[[{"res":"WOOD","amount":15000},{"res":"GLASS","amount":100}]]}},{"island":"week48","contract":{"start":{"x":152,"h":"NORTH","y":159},"budget":10000,"crew":3,"objs":[[{"res":"WOOD","amount":2000},{"res":"GLASS","amount":30},{"res":"FUR","amount":1000}]]}},{"island":"week51","contract":{"start":{"x":1,"h":"SOUTH","y":1},"budget":10000,"crew":25,"objs":[[{"res":"FUR","amount":3000},{"res":"WOOD","amount":3000},{"res":"GLASS","amount":100}]]}},{"island":"week02","contract":{"start":{"x":1,"h":"EAST","y":1},"budget":15000,"crew":4,"objs":[[{"res":"FLOWER","amount":40},{"res":"WOOD","amount":5000},{"res":"QUARTZ","amount":200},{"res":"GLASS","amount":50}]]}},{"island":"week11","contract":{"start":{"x":1,"h":"SOUTH","y":1},"budget":20000,"crew":15,"objs":[[{"res":"WOOD","amount":10000},{"res":"QUARTZ","amount":100},{"res":"LEATHER","amount":300},{"res":"ORE","amount":50}]]}},{"island":"week10","contract":{"start":{"x":158,"h":"NORTH","y":158},"budget":20000,"crew":15,"objs":[[{"res":"WOOD","amount":10000},{"res":"QUARTZ","amount":500},{"res":"LEATHER","amount":300},{"res":"RUM","amount":50}]]}},{"island":"week52","contract":{"start":{"x":1,"h":"EAST","y":1},"budget":10000,"crew":25,"objs":[[{"res":"FUR","amount":1000},{"res":"WOOD","amount":4000},{"res":"GLASS","amount":100}]]}},{"island":"week07","contract":{"start":{"x":1,"h":"NORTH","y":159},"budget":20000,"crew":25,"objs":[[{"res":"WOOD","amount":15000},{"res":"LEATHER","amount":30},{"res":"GLASS","amount":100}]]}},{"island":"week09","contract":{"start":{"x":1,"h":"EAST","y":1},"budget":20000,"crew":15,"objs":[[{"res":"WOOD","amount":10000},{"res":"LEATHER","amount":300},{"res":"GLASS","amount":50}]]}},{"island":"week50","contract":{"start":{"x":1,"h":"EAST","y":1},"budget":10000,"crew":3,"objs":[[{"res":"FUR","amount":5000},{"res":"WOOD","amount":1000},{"res":"GLASS","amount":300}]]}},{"island":"week12","contract":{"start":{"x":1,"h":"SOUTH","y":1},"budget":20000,"crew":5,"objs":[[{"res":"FUR","amount":400},{"res":"WOOD","amount":5000},{"res":"FLOWER","amount":1},{"res":"INGOT","amount":3},{"res":"LEATHER","amount":1000}]]}},{"island":"week05","contract":{"start":{"x":1,"h":"SOUTH","y":1},"budget":20000,"crew":25,"objs":[[{"res":"FUR","amount":2000},{"res":"WOOD","amount":7000},{"res":"GLASS","amount":100},{"res":"PLANK","amount":5000}]]}},{"island":"week49","contract":{"start":{"x":152,"h":"NORTH","y":159},"budget":10000,"crew":3,"objs":[[{"res":"WOOD","amount":5000},{"res":"SUGAR_CANE","amount":1000},{"res":"GLASS","amount":300}]]}},{"island":"week53","contract":{"start":{"x":1,"h":"SOUTH","y":1},"budget":10000,"crew":25,"objs":[[{"res":"FLOWER","amount":80},{"res":"WOOD","amount":5000},{"res":"GLASS","amount":100}]]}},{"island":"week46","contract":{"start":{"x":1,"h":"EAST","y":1},"budget":7000,"crew":15,"objs":[[{"res":"WOOD","amount":1000},{"res":"QUARTZ","amount":300},{"res":"FLOWER","amount":10}]]}},{"island":"week47","contract":{"start":{"x":1,"h":"EAST","y":1},"budget":7000,"crew":15,"objs":[[{"res":"WOOD","amount":1000},{"res":"QUARTZ","amount":300},{"res":"FLOWER","amount":10}]]}},{"island":"week01","contract":{"start":{"x":1,"h":"EAST","y":1},"budget":15000,"crew":4,"objs":[[{"res":"FLOWER","amount":80},{"res":"WOOD","amount":3000},{"res":"QUARTZ","amount":800},{"res":"PLANK","amount":1000}]]}}],"results":[{"result":"OK","island":"week05","collected":[[]],"remaining":152,"player":"qac"},{"result":"OK","island":"week12","collected":[[]],"remaining":19995,"player":"qdb"},{"result":"OK","island":"week06","collected":[[]],"remaining":13,"player":"qad"},{"result":"OK","island":"week02","collected":[[]],"remaining":369,"player":"qbc"},{"result":"OK","island":"week48","collected":[[]],"remaining":2894,"player":"qba"},{"result":"OK","island":"week49","collected":[[]],"remaining":487,"player":"qba"},{"result":"OK","island":"week06","collected":[[]],"remaining":370,"player":"qbc"},{"result":"OK","island":"week01","collected":[[]],"remaining":14996,"player":"qcb"},{"result":"OK","island":"week09","collected":[[]],"remaining":19787,"player":"qdf"},{"result":"OK","island":"week03","collected":[[]],"remaining":4058,"player":"qdb"},{"result":"OK","island":"week01","collected":[[]],"remaining":14516,"player":"qdf"},{"result":"OK","island":"week07","collected":[[]],"remaining":168,"player":"qbd"},{"result":"OK","island":"week52","collected":[[]],"remaining":9995,"player":"qab"},{"result":"OK","island":"week06","collected":[[]],"remaining":10796,"player":"qac"},{"result":"OK","island":"week49","collected":[[]],"remaining":5951,"player":"qaa"},{"result":"OK","island":"week07","collected":[[]],"remaining":317,"player":"qce"},{"result":"OK","island":"week06","collected":[[]],"remaining":158,"player":"qbd"},{"result":"OK","island":"week50","collected":[[]],"remaining":9392,"player":"qde"},{"result":"OK","island":"week48","collected":[[]],"remaining":466,"player":"qbd"},{"result":"OK","island":"week02","collected":[[]],"remaining":82,"player":"qba"},{"result":"OK","island":"week48","collected":[[]],"remaining":7886,"player":"qac"},{"result":"OK","island":"week48","collected":[[]],"remaining":15,"player":"qad"},{"result":"OK","island":"week05","collected":[[]],"remaining":68,"player":"qba"},{"result":"OK","island":"week09","collected":[[]],"remaining":19995,"player":"qdb"},{"result":"OK","island":"week47","collected":[[]],"remaining":4171,"player":"qcc"},{"result":"OK","island":"week09","collected":[[]],"remaining":7493,"player":"qdd"},{"result":"OK","island":"week52","collected":[[]],"remaining":182,"player":"qaa"},{"result":"OK","island":"week05","collected":[[]],"remaining":19998,"player":"qdb"},{"result":"KO","reason":"game error","island":"week10","player":"qae"},{"result":"OK","island":"week01","collected":[[]],"remaining":262,"player":"qcc"},{"result":"KO","reason":"game error","island":"week51","player":"qbb"},{"result":"OK","island":"week04","collected":[[]],"remaining":153,"player":"qac"},{"result":"OK","island":"week51","collected":[[]],"remaining":9998,"player":"qab"},{"result":"OK","island":"week48","collected":[[]],"remaining":45,"player":"qaf"},{"result":"OK","island":"week53","collected":[[]],"remaining":5212,"player":"qdd"},{"result":"OK","island":"week10","collected":[[]],"remaining":19995,"player":"qab"},{"result":"OK","island":"week07","collected":[[]],"remaining":19991,"player":"qda"},{"result":"KO","reason":"game error","island":"week52","player":"qde"},{"result":"OK","island":"week48","collected":[[]],"remaining":4479,"player":"qbe"},{"result":"OK","island":"week51","collected":[[]],"remaining":182,"player":"qdd"},{"result":"OK","island":"week07","collected":[[]],"remaining":1405,"player":"qdc"},{"result":"OK","island":"week46","collected":[[]],"remaining":1400,"player":"qaa"},{"result":"OK","island":"week51","collected":[[]],"remaining":2209,"player":"qca"},{"result":"OK","island":"week12","collected":[[]],"remaining":173,"player":"qaa"},{"result":"OK","island":"week12","collected":[[]],"remaining":7679,"player":"qba"},{"result":"KO","reason":"game error","island":"week50","player":"qbb"},{"result":"OK","island":"week03","collected":[[]],"remaining":8892,"player":"qda"},{"result":"OK","island":"week07","collected":[[]],"remaining":12976,"player":"qac"},{"result":"OK","island":"week51","collected":[[]],"remaining":1687,"player":"qcc"},{"result":"OK","island":"week05","collected":[[]],"remaining":272,"player":"qcd"},{"result":"OK","island":"week52","collected":[[]],"remaining":74,"player":"qdc"},{"result":"OK","island":"week04","collected":[[]],"remaining":156,"player":"qbe"},{"result":"OK","island":"week07","collected":[[]],"remaining":19876,"player":"qae"},{"result":"OK","island":"week53","collected":[[]],"remaining":175,"player":"qaa"},{"result":"OK","island":"week01","collected":[[]],"remaining":2270,"player":"qca"},{"result":"OK","island":"week47","collected":[[]],"remaining":222,"player":"qce"},{"result":"OK","island":"week04","collected":[[]],"remaining":9994,"player":"qbf"},{"result":"OK","island":"week11","collected":[[]],"remaining":19995,"player":"qdb"},{"result":"OK","island":"week49","collected":[[]],"remaining":9982,"player":"qde"},{"result":"OK","island":"week47","collected":[[]],"remaining":6996,"player":"qdb"},{"result":"OK","island":"week12","collected":[[]],"remaining":8823,"player":"qca"},{"result":"OK","island":"week51","collected":[[]],"remaining":5962,"player":"qaa"},{"result":"OK","island":"week49","collected":[[]],"remaining":9867,"player":"qae"},{"result":"OK","island":"week02","collected":[[]],"remaining":9002,"player":"qbe"},{"result":"KO","reason":"game error","island":"week01","player":"qac"},{"result":"OK","island":"week10","collected":[[]],"remaining":74,"player":"qdc"},{"result":"KO","reason":"game error","island":"week49","player":"qcf"},{"result":"KO","reason":"game error","island":"week02","player":"qbb"},{"result":"KO","reason":"game error","island":"week11","player":"qbb"},{"result":"OK","island":"week04","collected":[[]],"remaining":9996,"player":"qab"},{"result":"OK","island":"week02","collected":[[]],"remaining":28,"player":"qde"},{"result":"OK","island":"week05","collected":[[]],"remaining":148,"player":"qdd"},{"result":"OK","island":"week01","collected":[[]],"remaining":11124,"player":"qaa"},{"result":"OK","island":"week10","collected":[[]],"remaining":370,"player":"qbc"},{"result":"KO","reason":"game error","island":"week05","player":"qcf"},{"result":"OK","island":"week12","collected":[[]],"remaining":5650,"player":"qac"},{"result":"OK","island":"week09","collected":[[]],"remaining":177,"player":"qbd"},{"result":"KO","reason":"game error","island":"week05","player":"qae"},{"result":"OK","island":"week49","collected":[[]],"remaining":7829,"player":"qdc"},{"result":"OK","island":"week52","collected":[[]],"remaining":269,"player":"qcc"},{"result":"OK","island":"week46","collected":[[]],"remaining":6998,"player":"qcb"},{"result":"OK","island":"week06","collected":[[]],"remaining":4095,"player":"qba"},{"result":"OK","island":"week05","collected":[[]],"remaining":19996,"player":"qab"},{"result":"KO","reason":"game error","island":"week12","player":"qcf"},{"result":"OK","island":"week50","collected":[[]],"remaining":62,"player":"qdc"},{"result":"OK","island":"week04","collected":[[]],"remaining":78,"player":"qdc"},{"result":"KO","reason":"game error","island":"week10","player":"qca"},{"result":"OK","island":"week51","collected":[[]],"remaining":9997,"player":"qcb"},{"result":"OK","island":"week09","collected":[[]],"remaining":19995,"player":"qab"},{"result":"OK","island":"week11","collected":[[]],"remaining":19990,"player":"qda"},{"result":"OK","island":"week01","collected":[[]],"remaining":170,"player":"qbd"},{"result":"OK","island":"week06","collected":[[]],"remaining":19765,"player":"qdc"},{"result":"OK","island":"week53","collected":[[]],"remaining":45,"player":"qaf"},{"result":"OK","island":"week09","collected":[[]],"remaining":18613,"player":"qac"},{"result":"OK","island":"week12","collected":[[]],"remaining":16022,"player":"qcd"},{"result":"OK","island":"week49","collected":[[]],"remaining":37,"player":"qaf"},{"result":"OK","island":"week06","collected":[[]],"remaining":172,"player":"qaa"},{"result":"OK","island":"week04","collected":[[]],"remaining":227,"player":"qba"},{"result":"OK","island":"week07","collected":[[]],"remaining":19997,"player":"qab"},{"result":"OK","island":"week12","collected":[[]],"remaining":176,"player":"qbd"},{"result":"KO","reason":"game error","island":"week53","player":"qbb"},{"result":"OK","island":"week48","collected":[[]],"remaining":9994,"player":"qda"},{"result":"OK","island":"week47","collected":[[]],"remaining":268,"player":"qcd"},{"result":"OK","island":"week07","collected":[[]],"remaining":12,"player":"qad"},{"result":"OK","island":"week11","collected":[[]],"remaining":80,"player":"qdc"},{"result":"OK","island":"week11","collected":[[]],"remaining":3058,"player":"qdd"},{"result":"KO","reason":"game error","island":"week47","player":"qbb"},{"result":"OK","island":"week04","collected":[[]],"remaining":176,"player":"qbd"},{"result":"OK","island":"week01","collected":[[]],"remaining":2977,"player":"qdc"},{"result":"OK","island":"week01","collected":[[]],"remaining":373,"player":"qbc"},{"result":"OK","island":"week12","collected":[[]],"remaining":14,"player":"qad"},{"result":"OK","island":"week06","collected":[[]],"remaining":19996,"player":"qbf"},{"result":"OK","island":"week46","collected":[[]],"remaining":68,"player":"qdc"},{"result":"OK","island":"week48","collected":[[]],"remaining":7576,"player":"qca"},{"result":"OK","island":"week47","collected":[[]],"remaining":6997,"player":"qcb"},{"result":"OK","island":"week01","collected":[[]],"remaining":276,"player":"qcd"},{"result":"OK","island":"week51","collected":[[]],"remaining":172,"player":"qac"},{"result":"OK","island":"week03","collected":[[]],"remaining":1120,"player":"qcf"},{"result":"OK","island":"week02","collected":[[]],"remaining":264,"player":"qce"},{"result":"OK","island":"week04","collected":[[]],"remaining":295,"player":"qce"},{"result":"OK","island":"week52","collected":[[]],"remaining":163,"player":"qdd"},{"result":"OK","island":"week53","collected":[[]],"remaining":9996,"player":"qab"},{"result":"OK","island":"week02","collected":[[]],"remaining":164,"player":"qac"},{"result":"OK","island":"week11","collected":[[]],"remaining":19983,"player":"qde"},{"result":"OK","island":"week53","collected":[[]],"remaining":155,"player":"qac"},{"result":"OK","island":"week04","collected":[[]],"remaining":187,"player":"qaa"},{"result":"OK","island":"week53","collected":[[]],"remaining":179,"player":"qbd"},{"result":"OK","island":"week47","collected":[[]],"remaining":1533,"player":"qca"},{"result":"OK","island":"week02","collected":[[]],"remaining":14997,"player":"qab"},{"result":"OK","island":"week02","collected":[[]],"remaining":168,"player":"qbd"},{"result":"OK","island":"week52","collected":[[]],"remaining":1046,"player":"qcf"},{"result":"OK","island":"week07","collected":[[]],"remaining":35,"player":"qaf"},{"result":"OK","island":"week05","collected":[[]],"remaining":19995,"player":"qcb"},{"result":"OK","island":"week06","collected":[[]],"remaining":19882,"player":"qae"},{"result":"OK","island":"week12","collected":[[]],"remaining":19414,"player":"qdf"},{"result":"OK","island":"week09","collected":[[]],"remaining":272,"player":"qcc"},{"result":"OK","island":"week46","collected":[[]],"remaining":6995,"player":"qbf"},{"result":"OK","island":"week50","collected":[[]],"remaining":384,"player":"qbc"},{"result":"OK","island":"week04","collected":[[]],"remaining":900,"player":"qcf"},{"result":"OK","island":"week10","collected":[[]],"remaining":162,"player":"qdd"},{"result":"OK","island":"week51","collected":[[]],"remaining":284,"player":"qcd"},{"result":"OK","island":"week48","collected":[[]],"remaining":268,"player":"qcd"},{"result":"OK","island":"week50","collected":[[]],"remaining":167,"player":"qac"},{"result":"KO","reason":"game error","island":"week06","player":"qbb"},{"result":"OK","island":"week51","collected":[[]],"remaining":167,"player":"qbe"},{"result":"KO","reason":"game error","island":"week10","player":"qbb"},{"result":"OK","island":"week48","collected":[[]],"remaining":9981,"player":"qde"},{"result":"OK","island":"week48","collected":[[]],"remaining":80,"player":"qdc"},{"result":"OK","island":"week10","collected":[[]],"remaining":19991,"player":"qda"},{"result":"OK","island":"week49","collected":[[]],"remaining":9997,"player":"qdb"},{"result":"OK","island":"week10","collected":[[]],"remaining":19997,"player":"qbf"},{"result":"OK","island":"week05","collected":[[]],"remaining":19988,"player":"qda"},{"result":"OK","island":"week46","collected":[[]],"remaining":51,"player":"qaf"},{"result":"OK","island":"week03","collected":[[]],"remaining":12155,"player":"qbf"},{"result":"OK","island":"week01","collected":[[]],"remaining":1159,"player":"qcf"},{"result":"OK","island":"week12","collected":[[]],"remaining":287,"player":"qce"},{"result":"OK","island":"week48","collected":[[]],"remaining":9997,"player":"qcb"},{"result":"OK","island":"week49","collected":[[]],"remaining":381,"player":"qbc"},{"result":"OK","island":"week04","collected":[[]],"remaining":12,"player":"qad"},{"result":"OK","island":"week02","collected":[[]],"remaining":12587,"player":"qdf"},{"result":"KO","reason":"game error","island":"week11","player":"qae"},{"result":"KO","reason":"game error","island":"week09","player":"qde"},{"result":"OK","island":"week46","collected":[[]],"remaining":248,"player":"qce"},{"result":"OK","island":"week10","collected":[[]],"remaining":41,"player":"qaf"},{"result":"OK","island":"week03","collected":[[]],"remaining":38,"player":"qaf"},{"result":"OK","island":"week06","collected":[[]],"remaining":19988,"player":"qda"},{"result":"OK","island":"week10","collected":[[]],"remaining":158,"player":"qbd"},{"result":"OK","island":"week02","collected":[[]],"remaining":274,"player":"qcd"},{"result":"OK","island":"week04","collected":[[]],"remaining":9997,"player":"qdb"},{"result":"OK","island":"week01","collected":[[]],"remaining":255,"player":"qce"},{"result":"OK","island":"week09","collected":[[]],"remaining":8400,"player":"qca"},{"result":"OK","island":"week49","collected":[[]],"remaining":170,"player":"qbd"},{"result":"OK","island":"week11","collected":[[]],"remaining":3054,"player":"qca"},{"result":"OK","island":"week52","collected":[[]],"remaining":271,"player":"qcd"},{"result":"OK","island":"week03","collected":[[]],"remaining":247,"player":"qce"},{"result":"KO","reason":"game error","island":"week50","player":"qae"},{"result":"OK","island":"week03","collected":[[]],"remaining":19984,"player":"qde"},{"result":"OK","island":"week46","collected":[[]],"remaining":6995,"player":"qab"},{"result":"OK","island":"week05","collected":[[]],"remaining":19994,"player":"qbf"},{"result":"OK","island":"week09","collected":[[]],"remaining":19992,"player":"qda"},{"result":"OK","island":"week05","collected":[[]],"remaining":7344,"player":"qca"},{"result":"OK","island":"week01","collected":[[]],"remaining":29,"player":"qde"},{"result":"OK","island":"week50","collected":[[]],"remaining":9998,"player":"qcb"},{"result":"OK","island":"week46","collected":[[]],"remaining":6991,"player":"qda"},{"result":"OK","island":"week12","collected":[[]],"remaining":19978,"player":"qde"},{"result":"OK","island":"week48","collected":[[]],"remaining":171,"player":"qaa"},{"result":"OK","island":"week12","collected":[[]],"remaining":19994,"player":"qda"},{"result":"OK","island":"week05","collected":[[]],"remaining":374,"player":"qbc"},{"result":"OK","island":"week11","collected":[[]],"remaining":19997,"player":"qab"},{"result":"OK","island":"week04","collected":[[]],"remaining":2292,"player":"qdf"},{"result":"OK","island":"week09","collected":[[]],"remaining":82,"player":"qba"},{"result":"OK","island":"week11","collected":[[]],"remaining":10055,"player":"qaa"},{"result":"OK","island":"week11","collected":[[]],"remaining":157,"player":"qbe"},{"result":"OK","island":"week06","collected":[[]],"remaining":19980,"player":"qde"},{"result":"OK","island":"week07","collected":[[]],"remaining":8264,"player":"qba"},{"result":"OK","island":"week01","collected":[[]],"remaining":14993,"player":"qda"},{"result":"OK","island":"week11","collected":[[]],"remaining":162,"player":"qac"},{"result":"OK","island":"week02","collected":[[]],"remaining":39,"player":"qaf"},{"result":"OK","island":"week53","collected":[[]],"remaining":3097,"player":"qcc"},{"result":"OK","island":"week12","collected":[[]],"remaining":1155,"player":"qcc"},{"result":"OK","island":"week10","collected":[[]],"remaining":19995,"player":"qcb"},{"result":"OK","island":"week53","collected":[[]],"remaining":284,"player":"qcd"},{"result":"OK","island":"week47","collected":[[]],"remaining":180,"player":"qbe"},{"result":"OK","island":"week50","collected":[[]],"remaining":177,"player":"qaa"},{"result":"OK","island":"week47","collected":[[]],"remaining":180,"player":"qaa"},{"result":"OK","island":"week04","collected":[[]],"remaining":382,"player":"qbc"},{"result":"OK","island":"week02","collected":[[]],"remaining":14998,"player":"qdb"},{"result":"KO","reason":"game error","island":"week05","player":"qbb"},{"result":"OK","island":"week51","collected":[[]],"remaining":174,"player":"qce"},{"result":"KO","reason":"game error","island":"week10","player":"qac"},{"result":"OK","island":"week48","collected":[[]],"remaining":2365,"player":"qdd"},{"result":"OK","island":"week11","collected":[[]],"remaining":3812,"player":"qba"},{"result":"OK","island":"week05","collected":[[]],"remaining":14,"player":"qad"},{"result":"OK","island":"week02","collected":[[]],"remaining":14989,"player":"qda"},{"result":"OK","island":"week52","collected":[[]],"remaining":17,"player":"qad"},{"result":"OK","island":"week09","collected":[[]],"remaining":378,"player":"qbc"},{"result":"OK","island":"week47","collected":[[]],"remaining":2083,"player":"qbd"},{"result":"KO","reason":"game error","island":"week04","player":"qae"},{"result":"OK","island":"week52","collected":[[]],"remaining":9996,"player":"qcb"},{"result":"OK","island":"week52","collected":[[]],"remaining":391,"player":"qba"},{"result":"OK","island":"week52","collected":[[]],"remaining":9989,"player":"qda"},{"result":"OK","island":"week12","collected":[[]],"remaining":19995,"player":"qab"},{"result":"OK","island":"week46","collected":[[]],"remaining":3487,"player":"qdd"},{"result":"OK","island":"week05","collected":[[]],"remaining":5624,"player":"qcc"},{"result":"OK","island":"week05","collected":[[]],"remaining":10306,"player":"qdc"},{"result":"KO","reason":"game error","island":"week12","player":"qae"},{"result":"KO","reason":"game error","island":"week52","player":"qbb"},{"result":"OK","island":"week07","collected":[[]],"remaining":281,"player":"qcd"},{"result":"OK","island":"week12","collected":[[]],"remaining":19998,"player":"qcb"},{"result":"OK","island":"week50","collected":[[]],"remaining":2483,"player":"qbe"},{"result":"OK","island":"week01","collected":[[]],"remaining":4,"player":"qad"},{"result":"OK","island":"week52","collected":[[]],"remaining":37,"player":"qaf"},{"result":"KO","reason":"game error","island":"week53","player":"qbe"},{"result":"OK","island":"week48","collected":[[]],"remaining":9721,"player":"qae"},{"result":"OK","island":"week52","collected":[[]],"remaining":147,"player":"qac"},{"result":"OK","island":"week52","collected":[[]],"remaining":9995,"player":"qbf"},{"result":"OK","island":"week53","collected":[[]],"remaining":9998,"player":"qdb"},{"result":"OK","island":"week49","collected":[[]],"remaining":9996,"player":"qab"},{"result":"KO","reason":"game error","island":"week53","player":"qae"},{"result":"OK","island":"week04","collected":[[]],"remaining":262,"player":"qcd"},{"result":"OK","island":"week06","collected":[[]],"remaining":19998,"player":"qdb"},{"result":"OK","island":"week03","collected":[[]],"remaining":14725,"player":"qab"},{"result":"OK","island":"week10","collected":[[]],"remaining":1085,"player":"qcf"},{"result":"OK","island":"week52","collected":[[]],"remaining":9998,"player":"qdb"},{"result":"KO","reason":"game error","island":"week46","player":"qbe"},{"result":"OK","island":"week04","collected":[[]],"remaining":181,"player":"qda"},{"result":"OK","island":"week51","collected":[[]],"remaining":9997,"player":"qbf"},{"result":"OK","island":"week02","collected":[[]],"remaining":177,"player":"qaa"},{"result":"OK","island":"week50","collected":[[]],"remaining":9996,"player":"qdb"},{"result":"OK","island":"week07","collected":[[]],"remaining":19997,"player":"qbf"},{"result":"OK","island":"week09","collected":[[]],"remaining":26,"player":"qaf"},{"result":"OK","island":"week01","collected":[[]],"remaining":7419,"player":"qdd"},{"result":"OK","island":"week47","collected":[[]],"remaining":43,"player":"qae"},{"result":"OK","island":"week46","collected":[[]],"remaining":6995,"player":"qdb"},{"result":"OK","island":"week03","collected":[[]],"remaining":3206,"player":"qcc"},{"result":"OK","island":"week47","collected":[[]],"remaining":77,"player":"qba"},{"result":"OK","island":"week50","collected":[[]],"remaining":14,"player":"qad"},{"result":"OK","island":"week46","collected":[[]],"remaining":3457,"player":"qcc"},{"result":"OK","island":"week52","collected":[[]],"remaining":176,"player":"qbd"},{"result":"OK","island":"week11","collected":[[]],"remaining":1091,"player":"qcf"},{"result":"OK","island":"week05","collected":[[]],"remaining":31,"player":"qaf"},{"result":"OK","island":"week47","collected":[[]],"remaining":6991,"player":"qda"},{"result":"KO","reason":"game error","island":"week12","player":"qbe"},{"result":"OK","island":"week47","collected":[[]],"remaining":29,"player":"qde"},{"result":"OK","island":"week10","collected":[[]],"remaining":6025,"player":"qba"},{"result":"OK","island":"week53","collected":[[]],"remaining":213,"player":"qce"},{"result":"OK","island":"week48","collected":[[]],"remaining":221,"player":"qce"},{"result":"OK","island":"week47","collected":[[]],"remaining":8,"player":"qad"},{"result":"OK","island":"week03","collected":[[]],"remaining":5848,"player":"qdc"},{"result":"OK","island":"week03","collected":[[]],"remaining":78,"player":"qbb"},{"result":"OK","island":"week48","collected":[[]],"remaining":381,"player":"qbc"},{"result":"OK","island":"week09","collected":[[]],"remaining":273,"player":"qce"},{"result":"OK","island":"week49","collected":[[]],"remaining":264,"player":"qcc"},{"result":"OK","island":"week06","collected":[[]],"remaining":4789,"player":"qcc"},{"result":"OK","island":"week50","collected":[[]],"remaining":9996,"player":"qab"},{"result":"OK","island":"week02","collected":[[]],"remaining":77,"player":"qdc"},{"result":"OK","island":"week03","collected":[[]],"remaining":262,"player":"qcd"},{"result":"OK","island":"week04","collected":[[]],"remaining":162,"player":"qdd"},{"result":"OK","island":"week03","collected":[[]],"remaining":3635,"player":"qba"},{"result":"OK","island":"week51","collected":[[]],"remaining":1071,"player":"qcf"},{"result":"OK","island":"week48","collected":[[]],"remaining":9547,"player":"qdf"},{"result":"OK","island":"week46","collected":[[]],"remaining":21,"player":"qae"},{"result":"OK","island":"week46","collected":[[]],"remaining":374,"player":"qbc"},{"result":"OK","island":"week12","collected":[[]],"remaining":19996,"player":"qbf"},{"result":"OK","island":"week06","collected":[[]],"remaining":11718,"player":"qbe"},{"result":"OK","island":"week47","collected":[[]],"remaining":44,"player":"qaf"},{"result":"KO","reason":"game error","island":"week01","player":"qbe"},{"result":"OK","island":"week51","collected":[[]],"remaining":9721,"player":"qdc"},{"result":"OK","island":"week51","collected":[[]],"remaining":10,"player":"qad"},{"result":"OK","island":"week07","collected":[[]],"remaining":8948,"player":"qdd"},{"result":"OK","island":"week46","collected":[[]],"remaining":4335,"player":"qca"},{"result":"OK","island":"week53","collected":[[]],"remaining":9995,"player":"qcb"},{"result":"OK","island":"week53","collected":[[]],"remaining":73,"player":"qba"},{"result":"OK","island":"week01","collected":[[]],"remaining":14998,"player":"qbf"},{"result":"OK","island":"week10","collected":[[]],"remaining":19983,"player":"qde"},{"result":"OK","island":"week53","collected":[[]],"remaining":9991,"player":"qda"},{"result":"KO","reason":"game error","island":"week50","player":"qcf"},{"result":"OK","island":"week52","collected":[[]],"remaining":2278,"player":"qdf"},{"result":"OK","island":"week11","collected":[[]],"remaining":19998,"player":"qcb"},{"result":"OK","island":"week12","collected":[[]],"remaining":26,"player":"qaf"},{"result":"KO","reason":"game error","island":"week09","player":"qae"},{"result":"OK","island":"week51","collected":[[]],"remaining":8556,"player":"qdf"},{"result":"OK","island":"week06","collected":[[]],"remaining":19994,"player":"qcb"},{"result":"OK","island":"week11","collected":[[]],"remaining":264,"player":"qcd"},{"result":"OK","island":"week04","collected":[[]],"remaining":267,"player":"qcc"},{"result":"OK","island":"week03","collected":[[]],"remaining":2680,"player":"qbd"},{"result":"OK","island":"week05","collected":[[]],"remaining":297,"player":"qce"},{"result":"OK","island":"week47","collected":[[]],"remaining":58,"player":"qdc"},{"result":"OK","island":"week04","collected":[[]],"remaining":2426,"player":"qca"},{"result":"KO","reason":"game error","island":"week12","player":"qdd"},{"result":"KO","reason":"game error","island":"week04","player":"qde"},{"result":"OK","island":"week53","collected":[[]],"remaining":12,"player":"qad"},{"result":"OK","island":"week46","collected":[[]],"remaining":72,"player":"qba"},{"result":"OK","island":"week07","collected":[[]],"remaining":2391,"player":"qaa"},{"result":"OK","island":"week03","collected":[[]],"remaining":5957,"player":"qcb"},{"result":"KO","reason":"game error","island":"week48","player":"qbb"},{"result":"OK","island":"week51","collected":[[]],"remaining":83,"player":"qba"},{"result":"OK","island":"week01","collected":[[]],"remaining":14997,"player":"qab"},{"result":"KO","reason":"game error","island":"week01","player":"qbb"},{"result":"OK","island":"week10","collected":[[]],"remaining":5,"player":"qad"},{"result":"OK","island":"week53","collected":[[]],"remaining":1114,"player":"qcf"},{"result":"OK","island":"week04","collected":[[]],"remaining":42,"player":"qaf"},{"result":"OK","island":"week52","collected":[[]],"remaining":2441,"player":"qca"},{"result":"OK","island":"week50","collected":[[]],"remaining":274,"player":"qce"},{"result":"OK","island":"week49","collected":[[]],"remaining":305,"player":"qce"},{"result":"OK","island":"week50","collected":[[]],"remaining":5576,"player":"qca"},{"result":"OK","island":"week52","collected":[[]],"remaining":380,"player":"qbc"},{"result":"OK","island":"week50","collected":[[]],"remaining":9995,"player":"qbf"},{"result":"KO","reason":"game error","island":"week07","player":"qbb"},{"result":"OK","island":"week12","collected":[[]],"remaining":68,"player":"qdc"},{"result":"OK","island":"week09","collected":[[]],"remaining":19995,"player":"qbf"},{"result":"OK","island":"week49","collected":[[]],"remaining":271,"player":"qcd"},{"result":"KO","reason":"game error","island":"week48","player":"qcf"},{"result":"OK","island":"week47","collected":[[]],"remaining":4005,"player":"qdf"},{"result":"OK","island":"week03","collected":[[]],"remaining":11654,"player":"qca"},{"result":"OK","island":"week53","collected":[[]],"remaining":72,"player":"qdc"},{"result":"OK","island":"week03","collected":[[]],"remaining":17,"player":"qad"},{"result":"OK","island":"week07","collected":[[]],"remaining":1052,"player":"qcf"},{"result":"OK","island":"week46","collected":[[]],"remaining":17,"player":"qad"},{"result":"OK","island":"week02","collected":[[]],"remaining":5,"player":"qad"},{"result":"OK","island":"week01","collected":[[]],"remaining":14995,"player":"qdb"},{"result":"OK","island":"week47","collected":[[]],"remaining":6997,"player":"qbf"},{"result":"OK","island":"week52","collected":[[]],"remaining":279,"player":"qce"},{"result":"OK","island":"week05","collected":[[]],"remaining":170,"player":"qbd"},{"result":"OK","island":"week49","collected":[[]],"remaining":9996,"player":"qbf"},{"result":"OK","island":"week51","collected":[[]],"remaining":9990,"player":"qda"},{"result":"OK","island":"week10","collected":[[]],"remaining":157,"player":"qaa"},{"result":"KO","reason":"game error","island":"week03","player":"qae"},{"result":"OK","island":"week07","collected":[[]],"remaining":13700,"player":"qdf"},{"result":"OK","island":"week46","collected":[[]],"remaining":6605,"player":"qde"},{"result":"KO","reason":"game error","island":"week04","player":"qbb"},{"result":"OK","island":"week07","collected":[[]],"remaining":19995,"player":"qcb"},{"result":"KO","reason":"game error","island":"week01","player":"qae"},{"result":"OK","island":"week02","collected":[[]],"remaining":14996,"player":"qbf"},{"result":"OK","island":"week10","collected":[[]],"remaining":19998,"player":"qdb"},{"result":"OK","island":"week09","collected":[[]],"remaining":14,"player":"qad"},{"result":"OK","island":"week52","collected":[[]],"remaining":162,"player":"qbe"},{"result":"OK","island":"week53","collected":[[]],"remaining":9997,"player":"qbf"},{"result":"OK","island":"week47","collected":[[]],"remaining":377,"player":"qbc"},{"result":"OK","island":"week46","collected":[[]],"remaining":3695,"player":"qac"},{"result":"OK","island":"week49","collected":[[]],"remaining":9003,"player":"qdf"},{"result":"OK","island":"week49","collected":[[]],"remaining":6,"player":"qad"},{"result":"OK","island":"week09","collected":[[]],"remaining":74,"player":"qdc"},{"result":"OK","island":"week53","collected":[[]],"remaining":9450,"player":"qdf"},{"result":"OK","island":"week04","collected":[[]],"remaining":9996,"player":"qcb"},{"result":"OK","island":"week03","collected":[[]],"remaining":161,"player":"qbe"},{"result":"OK","island":"week51","collected":[[]],"remaining":382,"player":"qbc"},{"result":"KO","reason":"game error","island":"week02","player":"qae"},{"result":"OK","island":"week10","collected":[[]],"remaining":19657,"player":"qbe"},{"result":"OK","island":"week50","collected":[[]],"remaining":279,"player":"qcd"},{"result":"OK","island":"week03","collected":[[]],"remaining":5439,"player":"qdd"},{"result":"OK","island":"week50","collected":[[]],"remaining":168,"player":"qbd"},{"result":"OK","island":"week49","collected":[[]],"remaining":4283,"player":"qca"},{"result":"OK","island":"week46","collected":[[]],"remaining":283,"player":"qcd"},{"result":"KO","reason":"game error","island":"week46","player":"qbb"},{"result":"OK","island":"week12","collected":[[]],"remaining":64,"player":"qbc"},{"result":"OK","island":"week51","collected":[[]],"remaining":178,"player":"qbd"},{"result":"OK","island":"week48","collected":[[]],"remaining":9998,"player":"qdb"},{"result":"OK","island":"week06","collected":[[]],"remaining":6297,"player":"qca"},{"result":"OK","island":"week07","collected":[[]],"remaining":19997,"player":"qdb"},{"result":"OK","island":"week02","collected":[[]],"remaining":6539,"player":"qdd"},{"result":"OK","island":"week05","collected":[[]],"remaining":18874,"player":"qdf"},{"result":"OK","island":"week46","collected":[[]],"remaining":1063,"player":"qcf"},{"result":"OK","island":"week01","collected":[[]],"remaining":38,"player":"qaf"},{"result":"OK","island":"week11","collected":[[]],"remaining":161,"player":"qbd"},{"result":"OK","island":"week48","collected":[[]],"remaining":9995,"player":"qab"},{"result":"OK","island":"week46","collected":[[]],"remaining":175,"player":"qbd"},{"result":"OK","island":"week06","collected":[[]],"remaining":178,"player":"qdd"},{"result":"OK","island":"week11","collected":[[]],"remaining":4430,"player":"qcc"},{"result":"OK","island":"week07","collected":[[]],"remaining":14449,"player":"qbe"},{"result":"OK","island":"week07","collected":[[]],"remaining":376,"player":"qbc"},{"result":"OK","island":"week53","collected":[[]],"remaining":217,"player":"qca"},{"result":"OK","island":"week10","collected":[[]],"remaining":269,"player":"qce"},{"result":"OK","island":"week11","collected":[[]],"remaining":44,"player":"qaf"},{"result":"OK","island":"week51","collected":[[]],"remaining":9997,"player":"qdb"},{"result":"OK","island":"week49","collected":[[]],"remaining":9057,"player":"qbe"},{"result":"OK","island":"week07","collected":[[]],"remaining":3602,"player":"qcc"},{"result":"KO","reason":"game error","island":"week49","player":"qbb"},{"result":"OK","island":"week09","collected":[[]],"remaining":19995,"player":"qcb"},{"result":"OK","island":"week49","collected":[[]],"remaining":158,"player":"qac"},{"result":"OK","island":"week03","collected":[[]],"remaining":19755,"player":"qdf"},{"result":"OK","island":"week48","collected":[[]],"remaining":9994,"player":"qbf"},{"result":"OK","island":"week09","collected":[[]],"remaining":1070,"player":"qcf"},{"result":"OK","island":"week09","collected":[[]],"remaining":167,"player":"qaa"},{"result":"OK","island":"week10","collected":[[]],"remaining":19664,"player":"qdf"},{"result":"OK","island":"week51","collected":[[]],"remaining":44,"player":"qaf"},{"result":"OK","island":"week47","collected":[[]],"remaining":1072,"player":"qcf"},{"result":"OK","island":"week47","collected":[[]],"remaining":3718,"player":"qdd"},{"result":"OK","island":"week53","collected":[[]],"remaining":9980,"player":"qde"},{"result":"OK","island":"week02","collected":[[]],"remaining":8331,"player":"qca"},{"result":"OK","island":"week01","collected":[[]],"remaining":6433,"player":"qba"},{"result":"OK","island":"week05","collected":[[]],"remaining":178,"player":"qaa"},{"result":"OK","island":"week50","collected":[[]],"remaining":43,"player":"qaf"},{"result":"KO","reason":"game error","island":"week09","player":"qbb"},{"result":"OK","island":"week10","collected":[[]],"remaining":282,"player":"qcd"},{"result":"OK","island":"week51","collected":[[]],"remaining":9984,"player":"qde"},{"result":"OK","island":"week11","collected":[[]],"remaining":237,"player":"qce"},{"result":"OK","island":"week02","collected":[[]],"remaining":1162,"player":"qcf"},{"result":"KO","reason":"game error","island":"week52","player":"qae"},{"result":"OK","island":"week11","collected":[[]],"remaining":19997,"player":"qbf"},{"result":"OK","island":"week03","collected":[[]],"remaining":15772,"player":"qaa"},{"result":"OK","island":"week50","collected":[[]],"remaining":169,"player":"qdd"},{"result":"OK","island":"week09","collected":[[]],"remaining":2625,"player":"qbe"},{"result":"OK","island":"week47","collected":[[]],"remaining":6994,"player":"qab"},{"result":"OK","island":"week49","collected":[[]],"remaining":3628,"player":"qdd"},{"result":"OK","island":"week10","collected":[[]],"remaining":6165,"player":"qcc"},{"result":"OK","island":"week06","collected":[[]],"remaining":19994,"player":"qab"},{"result":"OK","island":"week48","collected":[[]],"remaining":274,"player":"qcc"},{"result":"OK","island":"week02","collected":[[]],"remaining":274,"player":"qcc"},{"result":"OK","island":"week11","collected":[[]],"remaining":19486,"player":"qdf"},{"result":"KO","reason":"game error","island":"week05","player":"qbe"},{"result":"OK","island":"week49","collected":[[]],"remaining":9991,"player":"qda"},{"result":"OK","island":"week49","collected":[[]],"remaining":9997,"player":"qcb"},{"result":"OK","island":"week03","collected":[[]],"remaining":365,"player":"qbc"},{"result":"OK","island":"week11","collected":[[]],"remaining":372,"player":"qbc"},{"result":"OK","island":"week50","collected":[[]],"remaining":6367,"player":"qba"},{"result":"OK","island":"week05","collected":[[]],"remaining":19981,"player":"qde"},{"result":"OK","island":"week06","collected":[[]],"remaining":824,"player":"qcf"},{"result":"KO","reason":"game error","island":"week12","player":"qbb"},{"result":"OK","island":"week06","collected":[[]],"remaining":18134,"player":"qdf"},{"result":"OK","island":"week47","collected":[[]],"remaining":1284,"player":"qac"},{"result":"OK","island":"week09","collected":[[]],"remaining":272,"player":"qcd"},{"result":"OK","island":"week50","collected":[[]],"remaining":9994,"player":"qda"},{"result":"OK","island":"week07","collected":[[]],"remaining":501,"player":"qca"},{"result":"OK","island":"week02","collected":[[]],"remaining":14998,"player":"qcb"},{"result":"OK","island":"week11","collected":[[]],"remaining":19,"player":"qad"},{"result":"KO","reason":"game error","island":"week51","player":"qae"},{"result":"OK","island":"week46","collected":[[]],"remaining":5067,"player":"qdf"},{"result":"OK","island":"week06","collected":[[]],"remaining":48,"player":"qaf"},{"result":"OK","island":"week06","collected":[[]],"remaining":7851,"player":"qcd"},{"result":"OK","island":"week06","collected":[[]],"remaining":264,"player":"qce"},{"result":"OK","island":"week50","collected":[[]],"remaining":9322,"player":"qdf"},{"result":"OK","island":"week50","collected":[[]],"remaining":3346,"player":"qcc"},{"result":"OK","island":"week53","collected":[[]],"remaining":381,"player":"qbc"},{"result":"OK","island":"week03","collected":[[]],"remaining":7542,"player":"qac"},{"result":"OK","island":"week07","collected":[[]],"remaining":19979,"player":"qde"}]}